django_query/__init__.py
django_query/djquery.py
django_query-1.0.6.dist-info/METADATA
django_query-1.0.6.dist-info/WHEEL
django_query-1.0.6.dist-info/top_level.txt
django_query-1.0.6.dist-info/RECORD
